[
  {
    "verse": 1,
    "text": "Oración de David. Inclina, oh Jehová, tu oído, y óyeme; Porque estoy afligido y menesteroso."
  },
  {
    "verse": 2,
    "text": "Guarda mi alma, porque soy pío: Salva tú, oh Dios mío, á tu siervo que en ti confía."
  },
  {
    "verse": 3,
    "text": "Ten misericordia de mí, oh Jehová: Porque á ti clamo todo el día."
  },
  {
    "verse": 4,
    "text": "Alegra el alma de tu siervo: Porque á ti, oh Señor, levanto mi alma."
  },
  {
    "verse": 5,
    "text": "Porque tú, Señor, eres bueno y perdonador, Y grande en misericordia para con todos los que te invocan."
  },
  {
    "verse": 6,
    "text": "Escucha, oh Jehová, mi oración, Y está atento á la voz de mis ruegos."
  },
  {
    "verse": 7,
    "text": "En el día de mi angustia te llamaré: Porque tú me respondes."
  },
  {
    "verse": 8,
    "text": "Oh Señor, ninguno hay como tú entre los dioses, Ni obras que igualen tus obras."
  },
  {
    "verse": 9,
    "text": "Todas las gentes que hiciste vendrán y se humillarán delante de ti, Señor; Y glorificarán tu nombre."
  },
  {
    "verse": 10,
    "text": "Porque tú eres grande, y hacedor de maravillas: Tú solo eres Dios."
  },
  {
    "verse": 11,
    "text": "Enséñame, oh Jehová, tu camino; caminaré yo en tu verdad: Consolida mi corazón para que tema tu nombre."
  },
  {
    "verse": 12,
    "text": "Te alabaré, oh Jehová Dios mío, con todo mi corazón; Y glorificaré tu nombre para siempre."
  },
  {
    "verse": 13,
    "text": "Porque tu misericordia es grande para conmigo; Y has librado mi alma del hoyo profundo."
  },
  {
    "verse": 14,
    "text": "Oh Dios, soberbios se levantaron contra mí, Y conspiración de fuertes ha buscado mi alma, Y no te pusieron delante de sí."
  },
  {
    "verse": 15,
    "text": "Mas tú, Señor, Dios misericordioso y clemente, Lento para la ira, y grande en misericordia y verdad;"
  },
  {
    "verse": 16,
    "text": "Mírame, y ten misericordia de mí: Da tu fortaleza á tu siervo, Y guarda al hijo de tu sierva."
  },
  {
    "verse": 17,
    "text": "Haz conmigo señal para bien, Y veánla los que me aborrecen, y sean avergonzados; Porque tú, Jehová, me ayudaste, y me consolaste."
  }
]