[
  {
    "verse": 1,
    "text": "BENDICE, alma mía, á Jehová. Jehová, Dios mío, mucho te has engrandecido; Haste vestido de gloria y de magnificencia."
  },
  {
    "verse": 2,
    "text": "El que se cubre de luz como de vestidura, Que extiende los cielos como una cortina;"
  },
  {
    "verse": 3,
    "text": "Que establece sus aposentos entre las aguas; El que pone las nubes por su carroza, El que anda sobre las alas del viento;"
  },
  {
    "verse": 4,
    "text": "El que hace á sus ángeles espíritus, Sus ministros al fuego flameante."
  },
  {
    "verse": 5,
    "text": "El fundó la tierra sobre sus basas; No será jamás removida."
  },
  {
    "verse": 6,
    "text": "Con el abismo, como con vestido, la cubriste; Sobre los montes estaban las aguas."
  },
  {
    "verse": 7,
    "text": "A tu reprensión huyeron; Al sonido de tu trueno se apresuraron;"
  },
  {
    "verse": 8,
    "text": "Subieron los montes, descendieron los valles, Al lugar que tú les fundaste."
  },
  {
    "verse": 9,
    "text": "Pusísteles término, el cual no traspasarán; Ni volverán á cubrir la tierra."
  },
  {
    "verse": 10,
    "text": "Tú eres el que envías las fuentes por los arroyos; Van entre los montes."
  },
  {
    "verse": 11,
    "text": "Abrevan á todas las bestias del campo: Quebrantan su sed los asnos montaraces."
  },
  {
    "verse": 12,
    "text": "Junto á aquellos habitarán las aves de los cielos; Entre las ramas dan voces."
  },
  {
    "verse": 13,
    "text": "El que riega los montes desde sus aposentos: Del fruto de sus obras se sacia la tierra."
  },
  {
    "verse": 14,
    "text": "El que hace producir el heno para las bestias, Y la hierba para el servicio del hombre; Sacando el pan de la tierra."
  },
  {
    "verse": 15,
    "text": "Y el vino que alegra el corazón del hombre, Y el aceite que hace lucir el rostro, Y el pan que sustenta el corazón del hombre."
  },
  {
    "verse": 16,
    "text": "Llénanse de jugo los árboles de Jehová, Los cedros del Líbano que él plantó."
  },
  {
    "verse": 17,
    "text": "Allí anidan las aves; En las hayas hace su casa la cigüeña."
  },
  {
    "verse": 18,
    "text": "Los montes altos para las cabras monteses; Las peñas, madrigueras para los conejos."
  },
  {
    "verse": 19,
    "text": "Hizo la luna para los tiempos: El sol conoce su ocaso."
  },
  {
    "verse": 20,
    "text": "Pone las tinieblas, y es la noche: En ella corretean todas las bestias de la selva."
  },
  {
    "verse": 21,
    "text": "Los leoncillos braman á la presa, Y para buscar de Dios su comida."
  },
  {
    "verse": 22,
    "text": "Sale el sol, recógense, Y échanse en sus cuevas."
  },
  {
    "verse": 23,
    "text": "Sale el hombre á su hacienda, Y á su labranza hasta la tarde."
  },
  {
    "verse": 24,
    "text": "Cuán muchas son tus obras, oh Jehová! Hiciste todas ellas con sabiduría: La tierra está llena de tus beneficios."
  },
  {
    "verse": 25,
    "text": "Asimismo esta gran mar y ancha de términos: En ella pescados sin número, Animales pequeños y grandes."
  },
  {
    "verse": 26,
    "text": "Allí andan navíos; Allí este leviathán que hiciste para que jugase en ella."
  },
  {
    "verse": 27,
    "text": "Todos ellos esperan en ti, Para que les des su comida á su tiempo."
  },
  {
    "verse": 28,
    "text": "Les das, recogen; Abres tu mano, hártanse de bien."
  },
  {
    "verse": 29,
    "text": "Escondes tu rostro, túrbanse: Les quitas el espíritu, dejan de ser, Y tórnanse en su polvo."
  },
  {
    "verse": 30,
    "text": "Envías tu espíritu, críanse: Y renuevas la haz de la tierra."
  },
  {
    "verse": 31,
    "text": "Sea la gloria de Jehová para siempre; Alégrese Jehová en sus obras;"
  },
  {
    "verse": 32,
    "text": "El cual mira á la tierra, y ella tiembla; Toca los montes, y humean."
  },
  {
    "verse": 33,
    "text": "A Jehová cantaré en mi vida: A mi Dios salmearé mientras viviere."
  },
  {
    "verse": 34,
    "text": "Serme ha suave hablar de él: Yo me alegraré en Jehová."
  },
  {
    "verse": 35,
    "text": "Sean consumidos de la tierra los pecadores, Y los impíos dejen de ser. Bendice, alma mía, á Jehová. Aleluya."
  }
]